hello_world_20251208/__init__.py
hello_world_20251208/hello_world.py
hello_world_20251208-1.0.0.dist-info/METADATA
hello_world_20251208-1.0.0.dist-info/WHEEL
hello_world_20251208-1.0.0.dist-info/top_level.txt
hello_world_20251208-1.0.0.dist-info/RECORD
