Metadata-Version: 2.4
Name: hello_world_20251208
Version: 1.0.0
Summary: Simple program that prints out 'Hello, world 2025!!!'
Author-email: koseiizawa <koseiizwa@gmail.com>
License: MIT
Project-URL: Homepage, https://github.com/koseiizawa/hello-world-2025
Requires-Python: >=3.8
